[
  {
    "level": 0,
    "stat_code": "97.01",
    "hs_code": "",
    "desc": "書画（肉筆のものに限るものとし、手作業で描き又は装飾した加工物及び第49.06項の図案を除く。）並びにコラージュ及びモザイクその他これらに類する装飾板",
    "rate": {},
    "unit": {},
    "law": [],
    "children": [
      {
        "level": 1,
        "stat_code": "97.01",
        "hs_code": "",
        "desc": "製作後100年を超えたもの",
        "rate": {},
        "unit": {},
        "law": [],
        "children": [
          {
            "level": 2,
            "stat_code": "9701.21",
            "hs_code": "000",
            "desc": "書画",
            "rate": {
              "基本": "無税",
              "暫定": "",
              "WTO協定": "(無税)",
              "特恵": "",
              "特別特恵": "",
              "EPA_シンガポール": "無税",
              "EPA_メキシコ": "無税",
              "EPA_マレーシア": "無税",
              "EPA_チリ": "無税",
              "EPA_タイ": "無税",
              "EPA_インドネシア": "無税",
              "EPA_ブルネイ": "無税",
              "EPA_アセアン": "無税",
              "EPA_フィリピン": "無税",
              "EPA_スイス": "無税",
              "EPA_ベトナム": "無税",
              "EPA_インド": "無税",
              "EPA_ペルー": "無税",
              "EPA_豪州": "無税",
              "EPA_モンゴル": "無税",
              "EPA_CPTPP": "無税",
              "EPA_欧州連合": "無税",
              "EPA_英国": "無税",
              "EPA_RCEP_アセアン豪州NZ": "無税",
              "EPA_RCEP_中国": "無税",
              "EPA_RCEP_韓国": "無税",
              "EPA_日米貿易協定": ""
            },
            "unit": {
              "I": "NO",
              "II": "KG"
            },
            "law": ["IL", "WA"],
            "children": []
          },
          {
            "level": 2,
            "stat_code": "9701.22",
            "hs_code": "000",
            "desc": "モザイク",
            "rate": {
              "基本": "無税",
              "暫定": "",
              "WTO協定": "(無税)",
              "特恵": "",
              "特別特恵": "",
              "EPA_シンガポール": "無税",
              "EPA_メキシコ": "無税",
              "EPA_マレーシア": "無税",
              "EPA_チリ": "無税",
              "EPA_タイ": "無税",
              "EPA_インドネシア": "無税",
              "EPA_ブルネイ": "無税",
              "EPA_アセアン": "無税",
              "EPA_フィリピン": "無税",
              "EPA_スイス": "無税",
              "EPA_ベトナム": "無税",
              "EPA_インド": "無税",
              "EPA_ペルー": "無税",
              "EPA_豪州": "無税",
              "EPA_モンゴル": "無税",
              "EPA_CPTPP": "無税",
              "EPA_欧州連合": "無税",
              "EPA_英国": "無税",
              "EPA_RCEP_アセアン豪州NZ": "無税",
              "EPA_RCEP_中国": "無税",
              "EPA_RCEP_韓国": "無税",
              "EPA_日米貿易協定": ""
            },
            "unit": {
              "I": "NO",
              "II": "KG"
            },
            "law": ["IL", "WA"],
            "children": []
          },
          {
            "level": 2,
            "stat_code": "9701.29",
            "hs_code": "000",
            "desc": "その他のもの",
            "rate": {
              "基本": "無税",
              "暫定": "",
              "WTO協定": "(無税)",
              "特恵": "",
              "特別特恵": "",
              "EPA_シンガポール": "無税",
              "EPA_メキシコ": "無税",
              "EPA_マレーシア": "無税",
              "EPA_チリ": "無税",
              "EPA_タイ": "無税",
              "EPA_インドネシア": "無税",
              "EPA_ブルネイ": "無税",
              "EPA_アセアン": "無税",
              "EPA_フィリピン": "無税",
              "EPA_スイス": "無税",
              "EPA_ベトナム": "無税",
              "EPA_インド": "無税",
              "EPA_ペルー": "無税",
              "EPA_豪州": "無税",
              "EPA_モンゴル": "無税",
              "EPA_CPTPP": "無税",
              "EPA_欧州連合": "無税",
              "EPA_英国": "無税",
              "EPA_RCEP_アセアン豪州NZ": "無税",
              "EPA_RCEP_中国": "無税",
              "EPA_RCEP_韓国": "無税",
              "EPA_日米貿易協定": ""
            },
            "unit": {
              "I": "NO",
              "II": "KG"
            },
            "law": ["IL", "WA"],
            "children": []
          }
        ]
      },
      {
        "level": 1,
        "stat_code": "97.01",
        "hs_code": "",
        "desc": "その他のもの",
        "rate": {},
        "unit": {},
        "law": [],
        "children": [
          {
            "level": 2,
            "stat_code": "9701.91",
            "hs_code": "000",
            "desc": "書画",
            "rate": {
              "基本": "無税",
              "暫定": "",
              "WTO協定": "(無税)",
              "特恵": "",
              "特別特恵": "",
              "EPA_シンガポール": "無税",
              "EPA_メキシコ": "無税",
              "EPA_マレーシア": "無税",
              "EPA_チリ": "無税",
              "EPA_タイ": "無税",
              "EPA_インドネシア": "無税",
              "EPA_ブルネイ": "無税",
              "EPA_アセアン": "無税",
              "EPA_フィリピン": "無税",
              "EPA_スイス": "無税",
              "EPA_ベトナム": "無税",
              "EPA_インド": "無税",
              "EPA_ペルー": "無税",
              "EPA_豪州": "無税",
              "EPA_モンゴル": "無税",
              "EPA_CPTPP": "無税",
              "EPA_欧州連合": "無税",
              "EPA_英国": "無税",
              "EPA_RCEP_アセアン豪州NZ": "無税",
              "EPA_RCEP_中国": "無税",
              "EPA_RCEP_韓国": "無税",
              "EPA_日米貿易協定": ""
            },
            "unit": {
              "I": "NO",
              "II": "KG"
            },
            "law": ["IL", "WA"],
            "children": []
          },
          {
            "level": 2,
            "stat_code": "9701.92",
            "hs_code": "000",
            "desc": "モザイク",
            "rate": {
              "基本": "無税",
              "暫定": "",
              "WTO協定": "(無税)",
              "特恵": "",
              "特別特恵": "",
              "EPA_シンガポール": "無税",
              "EPA_メキシコ": "無税",
              "EPA_マレーシア": "無税",
              "EPA_チリ": "無税",
              "EPA_タイ": "無税",
              "EPA_インドネシア": "無税",
              "EPA_ブルネイ": "無税",
              "EPA_アセアン": "無税",
              "EPA_フィリピン": "無税",
              "EPA_スイス": "無税",
              "EPA_ベトナム": "無税",
              "EPA_インド": "無税",
              "EPA_ペルー": "無税",
              "EPA_豪州": "無税",
              "EPA_モンゴル": "無税",
              "EPA_CPTPP": "無税",
              "EPA_欧州連合": "無税",
              "EPA_英国": "無税",
              "EPA_RCEP_アセアン豪州NZ": "無税",
              "EPA_RCEP_中国": "無税",
              "EPA_RCEP_韓国": "無税",
              "EPA_日米貿易協定": ""
            },
            "unit": {
              "I": "NO",
              "II": "KG"
            },
            "law": ["IL", "WA"],
            "children": []
          },
          {
            "level": 2,
            "stat_code": "9701.99",
            "hs_code": "000",
            "desc": "その他のもの",
            "rate": {
              "基本": "無税",
              "暫定": "",
              "WTO協定": "(無税)",
              "特恵": "",
              "特別特恵": "",
              "EPA_シンガポール": "無税",
              "EPA_メキシコ": "無税",
              "EPA_マレーシア": "無税",
              "EPA_チリ": "無税",
              "EPA_タイ": "無税",
              "EPA_インドネシア": "無税",
              "EPA_ブルネイ": "無税",
              "EPA_アセアン": "無税",
              "EPA_フィリピン": "無税",
              "EPA_スイス": "無税",
              "EPA_ベトナム": "無税",
              "EPA_インド": "無税",
              "EPA_ペルー": "無税",
              "EPA_豪州": "無税",
              "EPA_モンゴル": "無税",
              "EPA_CPTPP": "無税",
              "EPA_欧州連合": "無税",
              "EPA_英国": "無税",
              "EPA_RCEP_アセアン豪州NZ": "無税",
              "EPA_RCEP_中国": "無税",
              "EPA_RCEP_韓国": "無税",
              "EPA_日米貿易協定": ""
            },
            "unit": {
              "I": "NO",
              "II": "KG"
            },
            "law": ["IL", "WA"],
            "children": []
          }
        ]
      }
    ]
  },
  {
    "level": 0,
    "stat_code": "97.02",
    "hs_code": "",
    "desc": "銅版画、木版画、石版画その他の版画",
    "rate": {},
    "unit": {},
    "law": [],
    "children": [
      {
        "level": 1,
        "stat_code": "9702.10",
        "hs_code": "000",
        "desc": "製作後100年を超えたもの",
        "rate": {
          "基本": "無税",
          "暫定": "",
          "WTO協定": "(無税)",
          "特恵": "",
          "特別特恵": "",
          "EPA_シンガポール": "無税",
          "EPA_メキシコ": "無税",
          "EPA_マレーシア": "無税",
          "EPA_チリ": "無税",
          "EPA_タイ": "無税",
          "EPA_インドネシア": "無税",
          "EPA_ブルネイ": "無税",
          "EPA_アセアン": "無税",
          "EPA_フィリピン": "無税",
          "EPA_スイス": "無税",
          "EPA_ベトナム": "無税",
          "EPA_インド": "無税",
          "EPA_ペルー": "無税",
          "EPA_豪州": "無税",
          "EPA_モンゴル": "無税",
          "EPA_CPTPP": "無税",
          "EPA_欧州連合": "無税",
          "EPA_英国": "無税",
          "EPA_RCEP_アセアン豪州NZ": "無税",
          "EPA_RCEP_中国": "無税",
          "EPA_RCEP_韓国": "無税",
          "EPA_日米貿易協定": ""
        },
        "unit": {
          "I": "NO",
          "II": "KG"
        },
        "law": ["IL"],
        "children": []
      },
      {
        "level": 1,
        "stat_code": "9702.90",
        "hs_code": "000",
        "desc": "その他のもの",
        "rate": {
          "基本": "無税",
          "暫定": "",
          "WTO協定": "(無税)",
          "特恵": "",
          "特別特恵": "",
          "EPA_シンガポール": "無税",
          "EPA_メキシコ": "無税",
          "EPA_マレーシア": "無税",
          "EPA_チリ": "無税",
          "EPA_タイ": "無税",
          "EPA_インドネシア": "無税",
          "EPA_ブルネイ": "無税",
          "EPA_アセアン": "無税",
          "EPA_フィリピン": "無税",
          "EPA_スイス": "無税",
          "EPA_ベトナム": "無税",
          "EPA_インド": "無税",
          "EPA_ペルー": "無税",
          "EPA_豪州": "無税",
          "EPA_モンゴル": "無税",
          "EPA_CPTPP": "無税",
          "EPA_欧州連合": "無税",
          "EPA_英国": "無税",
          "EPA_RCEP_アセアン豪州NZ": "無税",
          "EPA_RCEP_中国": "無税",
          "EPA_RCEP_韓国": "無税",
          "EPA_日米貿易協定": ""
        },
        "unit": {
          "I": "NO",
          "II": "KG"
        },
        "law": ["IL"],
        "children": []
      }
    ]
  },
  {
    "level": 0,
    "stat_code": "97.03",
    "hs_code": "",
    "desc": "彫刻、塑像、鋳像その他これらに類する物品（材料を問わない。）",
    "rate": {},
    "unit": {},
    "law": [],
    "children": [
      {
        "level": 1,
        "stat_code": "9703.10",
        "hs_code": "000",
        "desc": "製作後100年を超えたもの",
        "rate": {
          "基本": "無税",
          "暫定": "",
          "WTO協定": "(無税)",
          "特恵": "",
          "特別特恵": "",
          "EPA_シンガポール": "無税",
          "EPA_メキシコ": "無税",
          "EPA_マレーシア": "無税",
          "EPA_チリ": "無税",
          "EPA_タイ": "無税",
          "EPA_インドネシア": "無税",
          "EPA_ブルネイ": "無税",
          "EPA_アセアン": "無税",
          "EPA_フィリピン": "無税",
          "EPA_スイス": "無税",
          "EPA_ベトナム": "無税",
          "EPA_インド": "無税",
          "EPA_ペルー": "無税",
          "EPA_豪州": "無税",
          "EPA_モンゴル": "無税",
          "EPA_CPTPP": "無税",
          "EPA_欧州連合": "無税",
          "EPA_英国": "無税",
          "EPA_RCEP_アセアン豪州NZ": "無税",
          "EPA_RCEP_中国": "無税",
          "EPA_RCEP_韓国": "無税",
          "EPA_日米貿易協定": ""
        },
        "unit": {
          "I": "NO",
          "II": "KG"
        },
        "law": ["IL"],
        "children": []
      },
      {
        "level": 1,
        "stat_code": "9703.90",
        "hs_code": "000",
        "desc": "その他のもの",
        "rate": {
          "基本": "無税",
          "暫定": "",
          "WTO協定": "(無税)",
          "特恵": "",
          "特別特恵": "",
          "EPA_シンガポール": "無税",
          "EPA_メキシコ": "無税",
          "EPA_マレーシア": "無税",
          "EPA_チリ": "無税",
          "EPA_タイ": "無税",
          "EPA_インドネシア": "無税",
          "EPA_ブルネイ": "無税",
          "EPA_アセアン": "無税",
          "EPA_フィリピン": "無税",
          "EPA_スイス": "無税",
          "EPA_ベトナム": "無税",
          "EPA_インド": "無税",
          "EPA_ペルー": "無税",
          "EPA_豪州": "無税",
          "EPA_モンゴル": "無税",
          "EPA_CPTPP": "無税",
          "EPA_欧州連合": "無税",
          "EPA_英国": "無税",
          "EPA_RCEP_アセアン豪州NZ": "無税",
          "EPA_RCEP_中国": "無税",
          "EPA_RCEP_韓国": "無税",
          "EPA_日米貿易協定": ""
        },
        "unit": {
          "I": "NO",
          "II": "KG"
        },
        "law": ["IL"],
        "children": []
      }
    ]
  },
  {
    "level": 0,
    "stat_code": "97.04",
    "hs_code": "",
    "desc": "",
    "rate": {},
    "unit": {},
    "law": [],
    "children": []
  },
  {
    "level": 0,
    "stat_code": "9704.00",
    "hs_code": "000",
    "desc": "郵便切手、収入印紙、郵便料金納付の印影、初日カバー、切手付き書簡類その他これらに類する物品（使用してあるかないかを問わないものとし、第49.07項のものを除く。）",
    "rate": {
      "基本": "無税",
      "暫定": "",
      "WTO協定": "(無税)",
      "特恵": "",
      "特別特恵": "",
      "EPA_シンガポール": "無税",
      "EPA_メキシコ": "無税",
      "EPA_マレーシア": "無税",
      "EPA_チリ": "無税",
      "EPA_タイ": "無税",
      "EPA_インドネシア": "無税",
      "EPA_ブルネイ": "無税",
      "EPA_アセアン": "無税",
      "EPA_フィリピン": "無税",
      "EPA_スイス": "無税",
      "EPA_ベトナム": "無税",
      "EPA_インド": "無税",
      "EPA_ペルー": "無税",
      "EPA_豪州": "無税",
      "EPA_モンゴル": "無税",
      "EPA_CPTPP": "無税",
      "EPA_欧州連合": "無税",
      "EPA_英国": "無税",
      "EPA_RCEP_アセアン豪州NZ": "無税",
      "EPA_RCEP_中国": "無税",
      "EPA_RCEP_韓国": "無税",
      "EPA_日米貿易協定": ""
    },
    "unit": {
      "I": "",
      "II": "KG"
    },
    "law": ["IL", "ST"],
    "children": []
  },
  {
    "level": 0,
    "stat_code": "97.05",
    "hs_code": "",
    "desc": "収集品及び標本（考古学、民族学、史学、動物学、植物学、鉱物学、解剖学、古生物学又は古銭に関するものに限る。）",
    "rate": {},
    "unit": {},
    "law": [],
    "children": [
      {
        "level": 1,
        "stat_code": "9705.10",
        "hs_code": "000",
        "desc": "収集品及び標本（考古学、民族学又は史学に関するものに限る。）",
        "rate": {
          "基本": "無税",
          "暫定": "",
          "WTO協定": "(無税)",
          "特恵": "",
          "特別特恵": "",
          "EPA_シンガポール": "無税",
          "EPA_メキシコ": "無税",
          "EPA_マレーシア": "無税",
          "EPA_チリ": "無税",
          "EPA_タイ": "無税",
          "EPA_インドネシア": "無税",
          "EPA_ブルネイ": "無税",
          "EPA_アセアン": "無税",
          "EPA_フィリピン": "無税",
          "EPA_スイス": "無税",
          "EPA_ベトナム": "無税",
          "EPA_インド": "無税",
          "EPA_ペルー": "無税",
          "EPA_豪州": "無税",
          "EPA_モンゴル": "無税",
          "EPA_CPTPP": "無税",
          "EPA_欧州連合": "無税",
          "EPA_英国": "無税",
          "EPA_RCEP_アセアン豪州NZ": "無税",
          "EPA_RCEP_中国": "無税",
          "EPA_RCEP_韓国": "無税",
          "EPA_日米貿易協定": ""
        },
        "unit": {
          "I": "",
          "II": "KG"
        },
        "law": ["IL", "WA", "HU"],
        "children": []
      },
      {
        "level": 1,
        "stat_code": "97.05",
        "hs_code": "",
        "desc": "収集品及び標本（動物学、植物学、鉱物学、解剖学又は古生物学に関するものに限る。）",
        "rate": {},
        "unit": {},
        "law": [],
        "children": [
          {
            "level": 2,
            "stat_code": "9705.21",
            "hs_code": "000",
            "desc": "人体の標本及びその部分品",
            "rate": {
              "基本": "無税",
              "暫定": "",
              "WTO協定": "(無税)",
              "特恵": "",
              "特別特恵": "",
              "EPA_シンガポール": "無税",
              "EPA_メキシコ": "無税",
              "EPA_マレーシア": "無税",
              "EPA_チリ": "無税",
              "EPA_タイ": "無税",
              "EPA_インドネシア": "無税",
              "EPA_ブルネイ": "無税",
              "EPA_アセアン": "無税",
              "EPA_フィリピン": "無税",
              "EPA_スイス": "無税",
              "EPA_ベトナム": "無税",
              "EPA_インド": "無税",
              "EPA_ペルー": "無税",
              "EPA_豪州": "無税",
              "EPA_モンゴル": "無税",
              "EPA_CPTPP": "無税",
              "EPA_欧州連合": "無税",
              "EPA_英国": "無税",
              "EPA_RCEP_アセアン豪州NZ": "無税",
              "EPA_RCEP_中国": "無税",
              "EPA_RCEP_韓国": "無税",
              "EPA_日米貿易協定": ""
            },
            "unit": {
              "I": "",
              "II": "KG"
            },
            "law": ["IL", "WA", "HU"],
            "children": []
          },
          {
            "level": 2,
            "stat_code": "9705.22",
            "hs_code": "000",
            "desc": "絶滅種又は絶滅危惧種のもの及びこれらの部分品",
            "rate": {
              "基本": "無税",
              "暫定": "",
              "WTO協定": "(無税)",
              "特恵": "",
              "特別特恵": "",
              "EPA_シンガポール": "無税",
              "EPA_メキシコ": "無税",
              "EPA_マレーシア": "無税",
              "EPA_チリ": "無税",
              "EPA_タイ": "無税",
              "EPA_インドネシア": "無税",
              "EPA_ブルネイ": "無税",
              "EPA_アセアン": "無税",
              "EPA_フィリピン": "無税",
              "EPA_スイス": "無税",
              "EPA_ベトナム": "無税",
              "EPA_インド": "無税",
              "EPA_ペルー": "無税",
              "EPA_豪州": "無税",
              "EPA_モンゴル": "無税",
              "EPA_CPTPP": "無税",
              "EPA_欧州連合": "無税",
              "EPA_英国": "無税",
              "EPA_RCEP_アセアン豪州NZ": "無税",
              "EPA_RCEP_中国": "無税",
              "EPA_RCEP_韓国": "無税",
              "EPA_日米貿易協定": ""
            },
            "unit": {
              "I": "",
              "II": "KG"
            },
            "law": ["IL", "WA", "HU"],
            "children": []
          },
          {
            "level": 2,
            "stat_code": "9705.29",
            "hs_code": "000",
            "desc": "その他のもの",
            "rate": {
              "基本": "無税",
              "暫定": "",
              "WTO協定": "(無税)",
              "特恵": "",
              "特別特恵": "",
              "EPA_シンガポール": "無税",
              "EPA_メキシコ": "無税",
              "EPA_マレーシア": "無税",
              "EPA_チリ": "無税",
              "EPA_タイ": "無税",
              "EPA_インドネシア": "無税",
              "EPA_ブルネイ": "無税",
              "EPA_アセアン": "無税",
              "EPA_フィリピン": "無税",
              "EPA_スイス": "無税",
              "EPA_ベトナム": "無税",
              "EPA_インド": "無税",
              "EPA_ペルー": "無税",
              "EPA_豪州": "無税",
              "EPA_モンゴル": "無税",
              "EPA_CPTPP": "無税",
              "EPA_欧州連合": "無税",
              "EPA_英国": "無税",
              "EPA_RCEP_アセアン豪州NZ": "無税",
              "EPA_RCEP_中国": "無税",
              "EPA_RCEP_韓国": "無税",
              "EPA_日米貿易協定": ""
            },
            "unit": {
              "I": "",
              "II": "KG"
            },
            "law": ["IL", "WA", "HU"],
            "children": []
          }
        ]
      },
      {
        "level": 1,
        "stat_code": "97.05",
        "hs_code": "",
        "desc": "収集品及び標本（古銭に関するものに限る。）",
        "rate": {},
        "unit": {},
        "law": [],
        "children": [
          {
            "level": 2,
            "stat_code": "9705.31",
            "hs_code": "000",
            "desc": "製作後100年を超えたもの",
            "rate": {
              "基本": "無税",
              "暫定": "",
              "WTO協定": "(無税)",
              "特恵": "",
              "特別特恵": "",
              "EPA_シンガポール": "無税",
              "EPA_メキシコ": "無税",
              "EPA_マレーシア": "無税",
              "EPA_チリ": "無税",
              "EPA_タイ": "無税",
              "EPA_インドネシア": "無税",
              "EPA_ブルネイ": "無税",
              "EPA_アセアン": "無税",
              "EPA_フィリピン": "無税",
              "EPA_スイス": "無税",
              "EPA_ベトナム": "無税",
              "EPA_インド": "無税",
              "EPA_ペルー": "無税",
              "EPA_豪州": "無税",
              "EPA_モンゴル": "無税",
              "EPA_CPTPP": "無税",
              "EPA_欧州連合": "無税",
              "EPA_英国": "無税",
              "EPA_RCEP_アセアン豪州NZ": "無税",
              "EPA_RCEP_中国": "無税",
              "EPA_RCEP_韓国": "無税",
              "EPA_日米貿易協定": ""
            },
            "unit": {
              "I": "",
              "II": "KG"
            },
            "law": ["IL", "WA", "HU"],
            "children": []
          },
          {
            "level": 2,
            "stat_code": "9705.39",
            "hs_code": "000",
            "desc": "その他のもの",
            "rate": {
              "基本": "無税",
              "暫定": "",
              "WTO協定": "(無税)",
              "特恵": "",
              "特別特恵": "",
              "EPA_シンガポール": "無税",
              "EPA_メキシコ": "無税",
              "EPA_マレーシア": "無税",
              "EPA_チリ": "無税",
              "EPA_タイ": "無税",
              "EPA_インドネシア": "無税",
              "EPA_ブルネイ": "無税",
              "EPA_アセアン": "無税",
              "EPA_フィリピン": "無税",
              "EPA_スイス": "無税",
              "EPA_ベトナム": "無税",
              "EPA_インド": "無税",
              "EPA_ペルー": "無税",
              "EPA_豪州": "無税",
              "EPA_モンゴル": "無税",
              "EPA_CPTPP": "無税",
              "EPA_欧州連合": "無税",
              "EPA_英国": "無税",
              "EPA_RCEP_アセアン豪州NZ": "無税",
              "EPA_RCEP_中国": "無税",
              "EPA_RCEP_韓国": "無税",
              "EPA_日米貿易協定": ""
            },
            "unit": {
              "I": "",
              "II": "KG"
            },
            "law": ["IL", "WA", "HU"],
            "children": []
          }
        ]
      }
    ]
  },
  {
    "level": 0,
    "stat_code": "97.06",
    "hs_code": "",
    "desc": "こつとう（製作後100年を超えたものに限る。）",
    "rate": {},
    "unit": {},
    "law": [],
    "children": [
      {
        "level": 1,
        "stat_code": "9706.10",
        "hs_code": "000",
        "desc": "製作後250年を超えたもの",
        "rate": {
          "基本": "無税",
          "暫定": "",
          "WTO協定": "(無税)",
          "特恵": "",
          "特別特恵": "",
          "EPA_シンガポール": "無税",
          "EPA_メキシコ": "無税",
          "EPA_マレーシア": "無税",
          "EPA_チリ": "無税",
          "EPA_タイ": "無税",
          "EPA_インドネシア": "無税",
          "EPA_ブルネイ": "無税",
          "EPA_アセアン": "無税",
          "EPA_フィリピン": "無税",
          "EPA_スイス": "無税",
          "EPA_ベトナム": "無税",
          "EPA_インド": "無税",
          "EPA_ペルー": "無税",
          "EPA_豪州": "無税",
          "EPA_モンゴル": "無税",
          "EPA_CPTPP": "無税",
          "EPA_欧州連合": "無税",
          "EPA_英国": "無税",
          "EPA_RCEP_アセアン豪州NZ": "無税",
          "EPA_RCEP_中国": "無税",
          "EPA_RCEP_韓国": "無税",
          "EPA_日米貿易協定": ""
        },
        "unit": {
          "I": "",
          "II": "KG"
        },
        "law": ["IL"],
        "children": []
      },
      {
        "level": 1,
        "stat_code": "9706.90",
        "hs_code": "000",
        "desc": "その他のもの",
        "rate": {
          "基本": "無税",
          "暫定": "",
          "WTO協定": "(無税)",
          "特恵": "",
          "特別特恵": "",
          "EPA_シンガポール": "無税",
          "EPA_メキシコ": "無税",
          "EPA_マレーシア": "無税",
          "EPA_チリ": "無税",
          "EPA_タイ": "無税",
          "EPA_インドネシア": "無税",
          "EPA_ブルネイ": "無税",
          "EPA_アセアン": "無税",
          "EPA_フィリピン": "無税",
          "EPA_スイス": "無税",
          "EPA_ベトナム": "無税",
          "EPA_インド": "無税",
          "EPA_ペルー": "無税",
          "EPA_豪州": "無税",
          "EPA_モンゴル": "無税",
          "EPA_CPTPP": "無税",
          "EPA_欧州連合": "無税",
          "EPA_英国": "無税",
          "EPA_RCEP_アセアン豪州NZ": "無税",
          "EPA_RCEP_中国": "無税",
          "EPA_RCEP_韓国": "無税",
          "EPA_日米貿易協定": ""
        },
        "unit": {
          "I": "",
          "II": "KG"
        },
        "law": ["IL"],
        "children": []
      }
    ]
  }
]
